{
	"always_show_minimap_viewport": true,
	"bold_folder_labels": true,
	"color_scheme": "Packages/Materialize/schemes/Material Dracula.tmTheme",
	"contrasted_quick_panel": true,
	"contrasted_sidebar": true,
	"contrasted_tabs": true,
	"font_face": "Fira Code",
	"font_size": 14,
	"icon_file_type_enable": true,
	"ignored_packages":
	[
		"Vintage"
	],
	"indent_guide_options":
	[
		"draw_normal",
		"draw_active"
	],
	"line_padding_bottom": 3,
	"line_padding_top": 3,
	"material_theme_accent_indigo": true,
	"material_theme_small_tab": false,
	"material_theme_tree_headings": true,
	"overlay_scroll_bars": "enabled",
	"replacements":
	{
		"js_class":
		{
			"case": false,
			"find": " class=\"",
			"greedy": true,
			"replace": " className=\""
		}
	},
	"tab_size": 2,
	"tabs_large": true,
	"theme": "Material Brogrammer.sublime-theme",
	"ubuntu_mono_ui": true
}
